github_utils/__init__.py
github_utils/__main__.py
github_utils/commands/__init__.py
github_utils/commands/create_repos.py
github_utils/commands/delete_repos.py
github_utils/commands/list_repos.py
github_utils-2.0.0.dist-info/COPYING
github_utils-2.0.0.dist-info/METADATA
github_utils-2.0.0.dist-info/WHEEL
github_utils-2.0.0.dist-info/entry_points.txt
github_utils-2.0.0.dist-info/top_level.txt
github_utils-2.0.0.dist-info/RECORD
