Metadata-Version: 2.1
Name: github-utils
Version: 2.0.0
Summary: A command-line tool to manage repositories on GitHub.
Home-page: https://github.com/he-yaowen/github-utils
Author: HE Yaowen
Author-email: he.yaowen@hotmail.com
Classifier: Development Status :: 3 - Alpha
Classifier: Environment :: Console
Classifier: Intended Audience :: Developers
Classifier: License :: OSI Approved :: GNU General Public License v3 (GPLv3)
Classifier: License :: OSI Approved :: MIT License
Classifier: Operating System :: OS Independent
Classifier: Programming Language :: Python
Classifier: Programming Language :: Python :: 3
Classifier: Programming Language :: Python :: 3.4
Classifier: Programming Language :: Python :: 3.5
Classifier: Programming Language :: Python :: 3.6
Classifier: Programming Language :: Python :: 3.7
License-File: COPYING
